{"type":"Feature","properties":{"ID_0":177,"ISO":"PHL","NAME_0":"Philippines","ID_1":43,"NAME_1":"Leyte","ID_2":857,"NAME_2":"Alangalang","ID_3":21553,"NAME_3":"Tombo","NL_NAME_3":"","VARNAME_3":"","TYPE_3":"Barangay","ENGTYPE_3":"Village","PROVINCE":"Leyte","REGION":"Eastern Visayas (Region VIII)"},"geometry":{"type":"MultiPolygon","coordinates":[[[[124.84848,11.18959],[124.825607,11.18792],[124.834213,11.1946],[124.837807,11.19642],[124.84024,11.19701],[124.842827,11.19664],[124.84568,11.198],[124.848106,11.1988],[124.84848,11.18959]]]]}}