{"type":"Feature","properties":{"ID_0":177,"ISO":"PHL","NAME_0":"Philippines","ID_1":61,"NAME_1":"Pangasinan","ID_2":1241,"NAME_2":"Alcala","ID_3":32055,"NAME_3":"Kasikis","NL_NAME_3":"","VARNAME_3":"","TYPE_3":"Barangay","ENGTYPE_3":"Village","PROVINCE":"Pangasinan","REGION":"Ilocos Region (Region I)"},"geometry":{"type":"MultiPolygon","coordinates":[[[[120.543373,15.86805],[120.548393,15.84632],[120.546051,15.84465],[120.544823,15.84552],[120.542,15.84677],[120.542473,15.84874],[120.542313,15.85055],[120.538979,15.86665],[120.541183,15.8673],[120.541878,15.86752],[120.543373,15.86805]]]]}}