{"type":"Feature","properties":{"ID_0":177,"ISO":"PHL","NAME_0":"Philippines","ID_1":55,"NAME_1":"Nueva Ecija","ID_2":1119,"NAME_2":"Aliaga","ID_3":29308,"NAME_3":"San Juan","NL_NAME_3":"","VARNAME_3":"","TYPE_3":"Barangay","ENGTYPE_3":"Village","PROVINCE":"Nueva Ecija","REGION":"Central Luzon (Region III)"},"geometry":{"type":"MultiPolygon","coordinates":[[[[120.873207,15.52318],[120.893661,15.52184],[120.896156,15.51859],[120.902107,15.51061],[120.890823,15.50487],[120.88681,15.50282],[120.867523,15.50579],[120.860603,15.50665],[120.869133,15.51932],[120.873207,15.52318]]]]}}