{"type":"Feature","properties":{"ID_0":177,"ISO":"PHL","NAME_0":"Philippines","ID_1":37,"NAME_1":"Isabela","ID_2":693,"NAME_2":"Aurora","ID_3":17430,"NAME_3":"San Pedro-San Pablo","NL_NAME_3":"","VARNAME_3":"Poblacion","TYPE_3":"Barangay","ENGTYPE_3":"Village","PROVINCE":"Isabela","REGION":"Cagayan Valley (Region II)"},"geometry":{"type":"MultiPolygon","coordinates":[[[[121.646408,17.008356],[121.653313,17.00993],[121.656746,16.998007],[121.656639,16.997976],[121.650986,16.996372],[121.646439,16.995026],[121.641891,16.994095],[121.638321,16.992813],[121.634506,17.00564],[121.646408,17.008356]]]]}}