{"type":"Feature","properties":{"ID_0":177,"ISO":"PHL","NAME_0":"Philippines","ID_1":56,"NAME_1":"Nueva Vizcaya","ID_2":1155,"NAME_2":"Bambang","ID_3":30207,"NAME_3":"Magsaysay Hills","NL_NAME_3":"","VARNAME_3":"","TYPE_3":"Barangay","ENGTYPE_3":"Village","PROVINCE":"Nueva Vizcaya","REGION":"Cagayan Valley (Region II)"},"geometry":{"type":"MultiPolygon","coordinates":[[[[121.114067,16.441931],[121.114441,16.438959],[121.114349,16.437731],[121.114014,16.436359],[121.113571,16.435209],[121.113197,16.434311],[121.113029,16.43375],[121.091209,16.434641],[121.0672,16.434811],[121.069687,16.447371],[121.114067,16.441931]]]]}}