{"type":"Feature","properties":{"ID_0":177,"ISO":"PHL","NAME_0":"Philippines","ID_1":6,"NAME_1":"Antique","ID_2":92,"NAME_2":"Barbaza","ID_3":1966,"NAME_3":"Mayos","NL_NAME_3":"","VARNAME_3":"","TYPE_3":"Barangay","ENGTYPE_3":"Village","PROVINCE":"Antique","REGION":"Western Visayas (Region VI)"},"geometry":{"type":"MultiPolygon","coordinates":[[[[122.103287,11.22493],[122.110031,11.22076],[122.097961,11.21123],[122.094009,11.21151],[122.081947,11.21591],[122.084969,11.22245],[122.087341,11.22243],[122.103287,11.22493]]]]}}