{"type":"Feature","properties":{"ID_0":177,"ISO":"PHL","NAME_0":"Philippines","ID_1":43,"NAME_1":"Leyte","ID_2":860,"NAME_2":"Barugo","ID_3":21602,"NAME_3":"Busay","NL_NAME_3":"","VARNAME_3":"","TYPE_3":"Barangay","ENGTYPE_3":"Village","PROVINCE":"Leyte","REGION":"Eastern Visayas (Region VIII)"},"geometry":{"type":"MultiPolygon","coordinates":[[[[124.770126,11.33059],[124.775162,11.33825],[124.784477,11.33255],[124.789497,11.32845],[124.794617,11.3237],[124.799393,11.31809],[124.797234,11.31192],[124.770126,11.33059]]]]}}