{"type":"Feature","properties":{"ID_0":177,"ISO":"PHL","NAME_0":"Philippines","ID_1":43,"NAME_1":"Leyte","ID_2":861,"NAME_2":"Bato","ID_3":21656,"NAME_3":"Plaridel","NL_NAME_3":"","VARNAME_3":"","TYPE_3":"Barangay","ENGTYPE_3":"Village","PROVINCE":"Leyte","REGION":"Eastern Visayas (Region VIII)"},"geometry":{"type":"MultiPolygon","coordinates":[[[[124.891937,10.35468],[124.894531,10.35489],[124.894913,10.3479],[124.895416,10.34178],[124.888268,10.34149],[124.889427,10.34717],[124.891937,10.35468]]]]}}