{"type":"Feature","properties":{"ID_0":177,"ISO":"PHL","NAME_0":"Philippines","ID_1":76,"NAME_1":"Surigao del Sur","ID_2":1516,"NAME_2":"Bislig City","ID_3":38838,"NAME_3":"Coleto","NL_NAME_3":"","VARNAME_3":"","TYPE_3":"Barangay","ENGTYPE_3":"Village","PROVINCE":"Surigao del Sur","REGION":"Caraga (Region XIII)"},"geometry":{"type":"MultiPolygon","coordinates":[[[[126.290947,8.22773],[126.289711,8.2255],[126.284592,8.21398],[126.283546,8.21446],[126.269814,8.21692],[126.249527,8.22438],[126.253349,8.23105],[126.258186,8.23782],[126.270699,8.23416],[126.278168,8.23011],[126.290947,8.22773]]]]}}