{"type":"Feature","properties":{"ID_0":177,"ISO":"PHL","NAME_0":"Philippines","ID_1":17,"NAME_1":"Bulacan","ID_2":283,"NAME_2":"Bocaue","ID_3":6412,"NAME_3":"Antipona","NL_NAME_3":"","VARNAME_3":"","TYPE_3":"Barangay","ENGTYPE_3":"Village","PROVINCE":"Bulacan","REGION":"Central Luzon (Region III)"},"geometry":{"type":"MultiPolygon","coordinates":[[[[120.921356,14.80213],[120.929771,14.80198],[120.932579,14.79931],[120.919807,14.79844],[120.920113,14.79953],[120.920639,14.80091],[120.921356,14.80213]]]]}}