{"type":"Feature","properties":{"ID_0":177,"ISO":"PHL","NAME_0":"Philippines","ID_1":31,"NAME_1":"Eastern Samar","ID_2":553,"NAME_2":"Borongan City","ID_3":13296,"NAME_3":"Camada","NL_NAME_3":"","VARNAME_3":"","TYPE_3":"Barangay","ENGTYPE_3":"Village","PROVINCE":"Eastern Samar","REGION":"Eastern Visayas (Region VIII)"},"geometry":{"type":"MultiPolygon","coordinates":[[[[125.432297,11.557],[125.459038,11.54156],[125.456734,11.54039],[125.456673,11.54037],[125.455368,11.53971],[125.450859,11.53711],[125.422279,11.54249],[125.432297,11.557]]]]}}