{"type":"Feature","properties":{"ID_0":177,"ISO":"PHL","NAME_0":"Philippines","ID_1":45,"NAME_1":"Marinduque","ID_2":924,"NAME_2":"Buenavista","ID_3":23436,"NAME_3":"Bagtingon","NL_NAME_3":"","VARNAME_3":"","TYPE_3":"Barangay","ENGTYPE_3":"Village","PROVINCE":"Marinduque","REGION":"MIMAROPA (Region IV-B)"},"geometry":{"type":"MultiPolygon","coordinates":[[[[121.975723,13.30869],[121.953819,13.27971],[121.948547,13.27372],[121.933113,13.27578],[121.931007,13.2759],[121.931953,13.29399],[121.965446,13.32067],[121.975723,13.30869]]]]}}