{"type":"Feature","properties":{"ID_0":177,"ISO":"PHL","NAME_0":"Philippines","ID_1":43,"NAME_1":"Leyte","ID_2":863,"NAME_2":"Burauen","ID_3":21758,"NAME_3":"Anonang","NL_NAME_3":"","VARNAME_3":"","TYPE_3":"Barangay","ENGTYPE_3":"Village","PROVINCE":"Leyte","REGION":"Eastern Visayas (Region VIII)"},"geometry":{"type":"MultiPolygon","coordinates":[[[[124.795013,10.95419],[124.807808,10.95414],[124.806511,10.95088],[124.805847,10.94551],[124.804993,10.94341],[124.802979,10.94235],[124.801727,10.94233],[124.797409,10.94222],[124.79438,10.94021],[124.795013,10.95419]]]]}}