{"type":"Feature","properties":{"ID_0":177,"ISO":"PHL","NAME_0":"Philippines","ID_1":14,"NAME_1":"Biliran","ID_2":205,"NAME_2":"Caibiran","ID_3":4696,"NAME_3":"Cabibihan","NL_NAME_3":"","VARNAME_3":"","TYPE_3":"Barangay","ENGTYPE_3":"Village","PROVINCE":"Biliran","REGION":"Eastern Visayas (Region VIII)"},"geometry":{"type":"MultiPolygon","coordinates":[[[[124.558853,11.5889],[124.561783,11.58354],[124.563652,11.58294],[124.561478,11.58135],[124.560448,11.58056],[124.559769,11.57989],[124.556664,11.57962],[124.554916,11.5811],[124.551033,11.58278],[124.556549,11.58523],[124.558037,11.58711],[124.558853,11.5889]]]]}}