{"type":"Feature","properties":{"ID_0":177,"ISO":"PHL","NAME_0":"Philippines","ID_1":42,"NAME_1":"Lanao del Sur","ID_2":823,"NAME_2":"Calanogas","ID_3":20561,"NAME_3":"Punud","NL_NAME_3":"","VARNAME_3":"","TYPE_3":"Barangay","ENGTYPE_3":"Village","PROVINCE":"Lanao del Sur","REGION":"Autonomous Region of Muslim Mindanao (ARMM)"},"geometry":{"type":"MultiPolygon","coordinates":[[[[124.03669,7.70404],[124.02726,7.68622],[124.021713,7.68798],[124.020714,7.68825],[124.031303,7.70699],[124.03669,7.70404]]]]}}