{"type":"Feature","properties":{"ID_0":177,"ISO":"PHL","NAME_0":"Philippines","ID_1":61,"NAME_1":"Pangasinan","ID_2":1254,"NAME_2":"Calasiao","ID_3":32405,"NAME_3":"Poblacion East","NL_NAME_3":"","VARNAME_3":"","TYPE_3":"Barangay","ENGTYPE_3":"Village","PROVINCE":"Pangasinan","REGION":"Ilocos Region (Region I)"},"geometry":{"type":"MultiPolygon","coordinates":[[[[120.36264,16.01334],[120.36364,16.008841],[120.362556,16.00841],[120.361504,16.008011],[120.360443,16.00765],[120.357552,16.01314],[120.359589,16.014099],[120.361343,16.01506],[120.36264,16.01334]]]]}}