{"type":"Feature","properties":{"ID_0":177,"ISO":"PHL","NAME_0":"Philippines","ID_1":20,"NAME_1":"Camarines Sur","ID_2":356,"NAME_2":"Canaman","ID_3":8282,"NAME_3":"Tibgao","NL_NAME_3":"","VARNAME_3":"Poblacion","TYPE_3":"Barangay","ENGTYPE_3":"Village","PROVINCE":"Camarines Sur","REGION":"Bicol Region (Region V)"},"geometry":{"type":"MultiPolygon","coordinates":[[[[123.161118,13.64728],[123.163002,13.64256],[123.155991,13.64012],[123.155182,13.64491],[123.158989,13.64663],[123.161118,13.64728]]]]}}