{"type":"Feature","properties":{"ID_0":177,"ISO":"PHL","NAME_0":"Philippines","ID_1":66,"NAME_1":"Samar","ID_2":1369,"NAME_2":"Catbalogan City","ID_3":35444,"NAME_3":"Pupua","NL_NAME_3":"","VARNAME_3":"","TYPE_3":"Barangay","ENGTYPE_3":"Village","PROVINCE":"Samar","REGION":"Eastern Visayas (Region VIII)"},"geometry":{"type":"MultiPolygon","coordinates":[[[[124.879333,11.83179],[124.882408,11.81691],[124.870773,11.81512],[124.857742,11.81239],[124.857613,11.81494],[124.85553,11.81687],[124.853508,11.8171],[124.86055,11.82967],[124.879333,11.83179]]]]}}