{"type":"Feature","properties":{"ID_0":177,"ISO":"PHL","NAME_0":"Philippines","ID_1":43,"NAME_1":"Leyte","ID_2":867,"NAME_2":"Dagami","ID_3":21966,"NAME_3":"Caanislagan","NL_NAME_3":"","VARNAME_3":"","TYPE_3":"Barangay","ENGTYPE_3":"Village","PROVINCE":"Leyte","REGION":"Eastern Visayas (Region VIII)"},"geometry":{"type":"MultiPolygon","coordinates":[[[[124.870453,11.09618],[124.872368,11.09292],[124.86351,11.08877],[124.86116,11.08804],[124.859627,11.0886],[124.859001,11.09055],[124.859894,11.09162],[124.865799,11.09418],[124.870453,11.09618]]]]}}