{"type":"Feature","properties":{"ID_0":177,"ISO":"PHL","NAME_0":"Philippines","ID_1":43,"NAME_1":"Leyte","ID_2":867,"NAME_2":"Dagami","ID_3":22013,"NAME_3":"Sawahon","NL_NAME_3":"","VARNAME_3":"","TYPE_3":"Barangay","ENGTYPE_3":"Village","PROVINCE":"Leyte","REGION":"Eastern Visayas (Region VIII)"},"geometry":{"type":"MultiPolygon","coordinates":[[[[124.884819,11.0739],[124.871513,11.06654],[124.8703,11.06918],[124.869247,11.07276],[124.873299,11.07355],[124.873428,11.07532],[124.881073,11.07835],[124.883759,11.07687],[124.884819,11.0739]]]]}}