{"type":"Feature","properties":{"ID_0":177,"ISO":"PHL","NAME_0":"Philippines","ID_1":16,"NAME_1":"Bukidnon","ID_2":261,"NAME_2":"Dangcagan","ID_3":5954,"NAME_3":"Osmea","NL_NAME_3":"","VARNAME_3":"","TYPE_3":"Barangay","ENGTYPE_3":"Village","PROVINCE":"Bukidnon","REGION":"Northern Mindanao (Region X)"},"geometry":{"type":"MultiPolygon","coordinates":[[[[124.975967,7.62517],[124.976601,7.62439],[124.978203,7.62331],[124.979462,7.62276],[124.980103,7.62205],[124.981506,7.62101],[124.987083,7.62064],[124.996964,7.61879],[124.994614,7.60901],[124.975647,7.61155],[124.975967,7.62517]]]]}}