{"type":"Feature","properties":{"ID_0":177,"ISO":"PHL","NAME_0":"Philippines","ID_1":5,"NAME_1":"Albay","ID_2":75,"NAME_2":"Daraga","ID_3":1317,"NAME_3":"Cullat","NL_NAME_3":"","VARNAME_3":"","TYPE_3":"Barangay","ENGTYPE_3":"Village","PROVINCE":"Albay","REGION":"Bicol Region (Region V)"},"geometry":{"type":"MultiPolygon","coordinates":[[[[123.705559,13.1731],[123.706413,13.174],[123.708313,13.17368],[123.71067,13.17267],[123.707527,13.16121],[123.706627,13.15681],[123.697617,13.16084],[123.700317,13.16437],[123.705559,13.1731]]]]}}