{"type":"Feature","properties":{"ID_0":177,"ISO":"PHL","NAME_0":"Philippines","ID_1":56,"NAME_1":"Nueva Vizcaya","ID_2":1159,"NAME_2":"Dupax Del Sur","ID_3":30282,"NAME_3":"Canabay","NL_NAME_3":"","VARNAME_3":"","TYPE_3":"Barangay","ENGTYPE_3":"Village","PROVINCE":"Nueva Vizcaya","REGION":"Cagayan Valley (Region II)"},"geometry":{"type":"MultiPolygon","coordinates":[[[[121.1306,16.28842],[121.155602,16.27923],[121.16124,16.267719],[121.147209,16.2626],[121.132858,16.27125],[121.1306,16.28842]]]]}}