{"type":"Feature","properties":{"ID_0":177,"ISO":"PHL","NAME_0":"Philippines","ID_1":66,"NAME_1":"Samar","ID_2":1371,"NAME_2":"Gandara","ID_3":35573,"NAME_3":"Santo Nio","NL_NAME_3":"","VARNAME_3":"","TYPE_3":"Barangay","ENGTYPE_3":"Village","PROVINCE":"Samar","REGION":"Eastern Visayas (Region VIII)"},"geometry":{"type":"MultiPolygon","coordinates":[[[[124.796997,12.04418],[124.801277,12.04488],[124.802582,12.04478],[124.802681,12.04399],[124.80304,12.04344],[124.803947,12.04259],[124.805687,12.04222],[124.806839,12.04207],[124.806488,12.03478],[124.806572,12.0324],[124.79689,12.03292],[124.796997,12.04418]]]]}}