{"type":"Feature","properties":{"ID_0":177,"ISO":"PHL","NAME_0":"Philippines","ID_1":31,"NAME_1":"Eastern Samar","ID_2":556,"NAME_2":"General Macarthur","ID_3":13427,"NAME_3":"Poblacion Barangay 1","NL_NAME_3":"","VARNAME_3":"","TYPE_3":"Barangay","ENGTYPE_3":"Village","PROVINCE":"Eastern Samar","REGION":"Eastern Visayas (Region VIII)"},"geometry":{"type":"MultiPolygon","coordinates":[[[[125.522987,11.26618],[125.540421,11.25959],[125.54039,11.25805],[125.541267,11.25709],[125.542633,11.25551],[125.542328,11.25458],[125.541313,11.25187],[125.534058,11.25412],[125.520653,11.26302],[125.522987,11.26618]]]]}}