{"type":"Feature","properties":{"ID_0":177,"ISO":"PHL","NAME_0":"Philippines","ID_1":79,"NAME_1":"Zambales","ID_2":1566,"NAME_2":"Iba","ID_3":39921,"NAME_3":"Zone 2 Poblacion","NL_NAME_3":"","VARNAME_3":"Aypa","TYPE_3":"Barangay","ENGTYPE_3":"Village","PROVINCE":"Zambales","REGION":"Central Luzon (Region III)"},"geometry":{"type":"MultiPolygon","coordinates":[[[[119.976196,15.32912],[119.982018,15.33007],[119.980423,15.32271],[119.979637,15.32362],[119.977097,15.3246],[119.976387,15.32503],[119.975563,15.32514],[119.976196,15.32912]]]]}}