{"type":"Feature","properties":{"ID_0":177,"ISO":"PHL","NAME_0":"Philippines","ID_1":51,"NAME_1":"Negros Occidental","ID_2":1033,"NAME_2":"Isabela","ID_3":27288,"NAME_3":"Barangay 7","NL_NAME_3":"","VARNAME_3":"Poblacion","TYPE_3":"Barangay","ENGTYPE_3":"Village","PROVINCE":"Negros Occidental","REGION":"Western Visayas (Region VI)"},"geometry":{"type":"MultiPolygon","coordinates":[[[[122.99614,10.2066],[122.999039,10.20509],[122.990936,10.20403],[122.987907,10.20366],[122.987709,10.20541],[122.99614,10.2066]]]]}}