{"type":"Feature","properties":{"ID_0":177,"ISO":"PHL","NAME_0":"Philippines","ID_1":66,"NAME_1":"Samar","ID_2":1373,"NAME_2":"Jiabong","ID_3":35609,"NAME_3":"Bawang","NL_NAME_3":"","VARNAME_3":"","TYPE_3":"Barangay","ENGTYPE_3":"Village","PROVINCE":"Samar","REGION":"Eastern Visayas (Region VIII)"},"geometry":{"type":"MultiPolygon","coordinates":[[[[124.925171,11.80826],[124.944443,11.80392],[124.943108,11.79317],[124.934937,11.78564],[124.926147,11.78439],[124.925636,11.79411],[124.92466,11.80465],[124.925171,11.80826]]]]}}