{"type":"Feature","properties":{"ID_0":177,"ISO":"PHL","NAME_0":"Philippines","ID_1":47,"NAME_1":"Metropolitan Manila","ID_2":950,"NAME_2":"Kalookan City","ID_3":24173,"NAME_3":"Barangay 127","NL_NAME_3":"","VARNAME_3":"","TYPE_3":"Barangay","ENGTYPE_3":"Village","PROVINCE":"Metropolitan Manila","REGION":"Metropolitan Manila"},"geometry":{"type":"MultiPolygon","coordinates":[[[[120.986656,14.642361],[120.988556,14.641742],[120.98838,14.641311],[120.988182,14.640841],[120.988022,14.64043],[120.987816,14.639951],[120.98587,14.640551],[120.986656,14.642361]]]]}}