{"type":"Feature","properties":{"ID_0":177,"ISO":"PHL","NAME_0":"Philippines","ID_1":6,"NAME_1":"Antique","ID_2":98,"NAME_2":"Laua-An","ID_3":2149,"NAME_3":"Maria","NL_NAME_3":"","VARNAME_3":"","TYPE_3":"Barangay","ENGTYPE_3":"Village","PROVINCE":"Antique","REGION":"Western Visayas (Region VI)"},"geometry":{"type":"MultiPolygon","coordinates":[[[[122.070999,11.09043],[122.07431,11.09669],[122.080353,11.0908],[122.089127,11.08926],[122.08831,11.08789],[122.084488,11.08377],[122.082123,11.08391],[122.078842,11.08661],[122.072006,11.08923],[122.070999,11.09043]]]]}}