{"type":"Feature","properties":{"ID_0":177,"ISO":"PHL","NAME_0":"Philippines","ID_1":36,"NAME_1":"Iloilo","ID_2":672,"NAME_2":"Leon","ID_3":16541,"NAME_3":"Tacuyong Norte","NL_NAME_3":"","VARNAME_3":"","TYPE_3":"Barangay","ENGTYPE_3":"Village","PROVINCE":"Iloilo","REGION":"Western Visayas (Region VI)"},"geometry":{"type":"MultiPolygon","coordinates":[[[[122.315361,10.82463],[122.323914,10.82275],[122.327309,10.82244],[122.328232,10.8196],[122.324966,10.81214],[122.322792,10.81203],[122.31855,10.81773],[122.319397,10.8214],[122.318466,10.82322],[122.315361,10.82463]]]]}}