{"type":"Feature","properties":{"ID_0":177,"ISO":"PHL","NAME_0":"Philippines","ID_1":36,"NAME_1":"Iloilo","ID_2":672,"NAME_2":"Leon","ID_3":16529,"NAME_3":"Oluangan","NL_NAME_3":"","VARNAME_3":"","TYPE_3":"Barangay","ENGTYPE_3":"Village","PROVINCE":"Iloilo","REGION":"Western Visayas (Region VI)"},"geometry":{"type":"MultiPolygon","coordinates":[[[[122.379471,10.82616],[122.375679,10.81615],[122.359207,10.82066],[122.361237,10.82583],[122.362648,10.82791],[122.369377,10.83123],[122.379471,10.82616]]]]}}