{"type":"Feature","properties":{"ID_0":177,"ISO":"PHL","NAME_0":"Philippines","ID_1":42,"NAME_1":"Lanao del Sur","ID_2":833,"NAME_2":"Lumbayanague","ID_3":20748,"NAME_3":"Lamin","NL_NAME_3":"","VARNAME_3":"","TYPE_3":"Barangay","ENGTYPE_3":"Village","PROVINCE":"Lanao del Sur","REGION":"Autonomous Region of Muslim Mindanao (ARMM)"},"geometry":{"type":"MultiPolygon","coordinates":[[[[124.287857,7.76402],[124.296783,7.76702],[124.297417,7.7623],[124.291649,7.7568],[124.290253,7.75816],[124.289612,7.75966],[124.287857,7.76402]]]]}}