{"type":"Feature","properties":{"ID_0":177,"ISO":"PHL","NAME_0":"Philippines","ID_1":36,"NAME_1":"Iloilo","ID_2":673,"NAME_2":"Maasin","ID_3":16552,"NAME_3":"AGROCEL Pob","NL_NAME_3":"","VARNAME_3":"Aguinaldo-Roxas--Celso Ma","TYPE_3":"Barangay","ENGTYPE_3":"Village","PROVINCE":"Iloilo","REGION":"Western Visayas (Region VI)"},"geometry":{"type":"MultiPolygon","coordinates":[[[[122.432312,10.89345],[122.432777,10.89345],[122.433403,10.89352],[122.434486,10.89391],[122.433647,10.89097],[122.431892,10.8914],[122.431969,10.89198],[122.432022,10.89268],[122.432312,10.89345]]]]}}