{"type":"Feature","properties":{"ID_0":177,"ISO":"PHL","NAME_0":"Philippines","ID_1":42,"NAME_1":"Lanao del Sur","ID_2":834,"NAME_2":"Madalum","ID_3":20779,"NAME_3":"Madaya","NL_NAME_3":"","VARNAME_3":"","TYPE_3":"Barangay","ENGTYPE_3":"Village","PROVINCE":"Lanao del Sur","REGION":"Autonomous Region of Muslim Mindanao (ARMM)"},"geometry":{"type":"MultiPolygon","coordinates":[[[[124.106651,7.88039],[124.108688,7.88187],[124.110733,7.87895],[124.107948,7.87329],[124.105942,7.87543],[124.10331,7.8783],[124.106651,7.88039]]]]}}