{"type":"Feature","properties":{"ID_0":177,"ISO":"PHL","NAME_0":"Philippines","ID_1":61,"NAME_1":"Pangasinan","ID_2":1262,"NAME_2":"Malasiqui","ID_3":32598,"NAME_3":"Manggan-Dampay","NL_NAME_3":"","VARNAME_3":"","TYPE_3":"Barangay","ENGTYPE_3":"Village","PROVINCE":"Pangasinan","REGION":"Ilocos Region (Region I)"},"geometry":{"type":"MultiPolygon","coordinates":[[[[120.498734,15.95556],[120.499184,15.94666],[120.497276,15.94631],[120.487839,15.94702],[120.487213,15.95527],[120.498611,15.957],[120.498734,15.95556]]]]}}