{"type":"Feature","properties":{"ID_0":177,"ISO":"PHL","NAME_0":"Philippines","ID_1":61,"NAME_1":"Pangasinan","ID_2":1265,"NAME_2":"Mangatarem","ID_3":32765,"NAME_3":"Zamora","NL_NAME_3":"","VARNAME_3":"Poblacion","TYPE_3":"Barangay","ENGTYPE_3":"Village","PROVINCE":"Pangasinan","REGION":"Ilocos Region (Region I)"},"geometry":{"type":"MultiPolygon","coordinates":[[[[120.303574,15.78086],[120.307617,15.78156],[120.306511,15.77996],[120.305817,15.77899],[120.305481,15.77833],[120.303574,15.78086]]]]}}