{"type":"Feature","properties":{"ID_0":177,"ISO":"PHL","NAME_0":"Philippines","ID_1":47,"NAME_1":"Metropolitan Manila","ID_2":955,"NAME_2":"Manila","ID_3":24810,"NAME_3":"Barangay 453","NL_NAME_3":"","VARNAME_3":"","TYPE_3":"Barangay","ENGTYPE_3":"Village","PROVINCE":"Metropolitan Manila","REGION":"Metropolitan Manila"},"geometry":{"type":"MultiPolygon","coordinates":[[[[120.992607,14.610351],[120.992882,14.610591],[120.993111,14.610822],[120.993462,14.611021],[120.993561,14.61093],[120.994438,14.61005],[120.994148,14.60979],[120.993912,14.609561],[120.993637,14.609321],[120.993019,14.609941],[120.992607,14.610351]]]]}}