{"type":"Feature","properties":{"ID_0":177,"ISO":"PHL","NAME_0":"Philippines","ID_1":42,"NAME_1":"Lanao del Sur","ID_2":841,"NAME_2":"Masiu","ID_3":21050,"NAME_3":"Kalilangan","NL_NAME_3":"","VARNAME_3":"","TYPE_3":"Barangay","ENGTYPE_3":"Village","PROVINCE":"Lanao del Sur","REGION":"Autonomous Region of Muslim Mindanao (ARMM)"},"geometry":{"type":"MultiPolygon","coordinates":[[[[124.312813,7.82059],[124.31498,7.8203],[124.312424,7.81616],[124.304207,7.81328],[124.303947,7.81412],[124.303307,7.81518],[124.303123,7.81583],[124.30307,7.81674],[124.303223,7.81742],[124.303413,7.81838],[124.303497,7.81952],[124.303413,7.8206],[124.312813,7.82059]]]]}}