{"type":"Feature","properties":{"ID_0":177,"ISO":"PHL","NAME_0":"Philippines","ID_1":43,"NAME_1":"Leyte","ID_2":881,"NAME_2":"Matag-Ob","ID_3":22445,"NAME_3":"San Sebastian","NL_NAME_3":"","VARNAME_3":"","TYPE_3":"Barangay","ENGTYPE_3":"Village","PROVINCE":"Leyte","REGION":"Eastern Visayas (Region VIII)"},"geometry":{"type":"MultiPolygon","coordinates":[[[[124.477951,11.14604],[124.492554,11.14099],[124.509552,11.13647],[124.511414,11.12914],[124.505547,11.12082],[124.478828,11.13293],[124.470108,11.13826],[124.472481,11.14069],[124.476097,11.14444],[124.477951,11.14604]]]]}}