{"type":"Feature","properties":{"ID_0":177,"ISO":"PHL","NAME_0":"Philippines","ID_1":43,"NAME_1":"Leyte","ID_2":885,"NAME_2":"Ormoc City","ID_3":22558,"NAME_3":"Cabintan","NL_NAME_3":"","VARNAME_3":"","TYPE_3":"Barangay","ENGTYPE_3":"Village","PROVINCE":"Leyte","REGION":"Eastern Visayas (Region VIII)"},"geometry":{"type":"MultiPolygon","coordinates":[[[[124.711433,11.12075],[124.718224,11.11338],[124.723824,11.10729],[124.691292,11.08777],[124.663048,11.07202],[124.661697,11.07105],[124.654518,11.08441],[124.711433,11.12075]]]]}}