{"type":"Feature","properties":{"ID_0":177,"ISO":"PHL","NAME_0":"Philippines","ID_1":62,"NAME_1":"Quezon","ID_2":1309,"NAME_2":"Pagbilao","ID_3":34123,"NAME_3":"Barangay 6 Tambak","NL_NAME_3":"","VARNAME_3":"Poblacion","TYPE_3":"Barangay","ENGTYPE_3":"Village","PROVINCE":"Quezon","REGION":"CALABARZON (Region IV-A)"},"geometry":{"type":"MultiPolygon","coordinates":[[[[121.694618,13.97588],[121.693062,13.97385],[121.691307,13.97308],[121.688667,13.97188],[121.687881,13.97367],[121.689919,13.9747],[121.692139,13.97564],[121.694618,13.97588]]]]}}