{"type":"Feature","properties":{"ID_0":177,"ISO":"PHL","NAME_0":"Philippines","ID_1":66,"NAME_1":"Samar","ID_2":1378,"NAME_2":"Paranas","ID_3":35739,"NAME_3":"Lokilokon","NL_NAME_3":"","VARNAME_3":"","TYPE_3":"Barangay","ENGTYPE_3":"Village","PROVINCE":"Samar","REGION":"Eastern Visayas (Region VIII)"},"geometry":{"type":"MultiPolygon","coordinates":[[[[125.114082,11.81878],[125.116501,11.8004],[125.093803,11.79937],[125.098083,11.8062],[125.095383,11.81417],[125.100487,11.81549],[125.114082,11.81878]]]]}}