{"type":"Feature","properties":{"ID_0":177,"ISO":"PHL","NAME_0":"Philippines","ID_1":47,"NAME_1":"Metropolitan Manila","ID_2":960,"NAME_2":"Pasay City","ID_3":25492,"NAME_3":"Barangay 20","NL_NAME_3":"","VARNAME_3":"","TYPE_3":"Barangay","ENGTYPE_3":"Village","PROVINCE":"Metropolitan Manila","REGION":"Metropolitan Manila"},"geometry":{"type":"MultiPolygon","coordinates":[[[[120.991386,14.557651],[120.991501,14.557251],[120.991646,14.55685],[120.990677,14.556551],[120.990417,14.55648],[120.990303,14.556841],[120.99015,14.557281],[120.991386,14.557651]]]]}}