{"type":"Feature","properties":{"ID_0":177,"ISO":"PHL","NAME_0":"Philippines","ID_1":47,"NAME_1":"Metropolitan Manila","ID_2":960,"NAME_2":"Pasay City","ID_3":25541,"NAME_3":"Barangay 63","NL_NAME_3":"","VARNAME_3":"","TYPE_3":"Barangay","ENGTYPE_3":"Village","PROVINCE":"Metropolitan Manila","REGION":"Metropolitan Manila"},"geometry":{"type":"MultiPolygon","coordinates":[[[[121.00145,14.55245],[121.001488,14.552111],[121.001152,14.551991],[121.001007,14.55189],[121.000267,14.55158],[121.000252,14.551691],[121.000206,14.55181],[121.000183,14.551961],[121.001122,14.55232],[121.001236,14.552371],[121.001328,14.552421],[121.00145,14.55245]]]]}}