{"type":"Feature","properties":{"ID_0":177,"ISO":"PHL","NAME_0":"Philippines","ID_1":47,"NAME_1":"Metropolitan Manila","ID_2":960,"NAME_2":"Pasay City","ID_3":25556,"NAME_3":"Barangay 77","NL_NAME_3":"","VARNAME_3":"","TYPE_3":"Barangay","ENGTYPE_3":"Village","PROVINCE":"Metropolitan Manila","REGION":"Metropolitan Manila"},"geometry":{"type":"MultiPolygon","coordinates":[[[[120.995392,14.53861],[120.996033,14.53887],[120.997078,14.539341],[120.9972,14.539381],[120.997391,14.539411],[120.997566,14.539381],[120.997742,14.539341],[120.998039,14.53746],[120.997223,14.537431],[120.997192,14.537641],[120.995636,14.537591],[120.995392,14.53861]]]]}}