{"type":"Feature","properties":{"ID_0":177,"ISO":"PHL","NAME_0":"Philippines","ID_1":75,"NAME_1":"Surigao del Norte","ID_2":1504,"NAME_2":"Placer","ID_3":38648,"NAME_3":"Bugas-Bugas","NL_NAME_3":"","VARNAME_3":"","TYPE_3":"Barangay","ENGTYPE_3":"Village","PROVINCE":"Surigao del Norte","REGION":"Caraga (Region XIII)"},"geometry":{"type":"MultiPolygon","coordinates":[[[[125.56881,9.64525],[125.569344,9.64636],[125.570541,9.64786],[125.571716,9.64904],[125.574226,9.65137],[125.575546,9.65353],[125.582558,9.64946],[125.593033,9.64338],[125.588966,9.63939],[125.56881,9.64525]]]]}}