{"type":"Feature","properties":{"ID_0":177,"ISO":"PHL","NAME_0":"Philippines","ID_1":71,"NAME_1":"South Cotabato","ID_2":1435,"NAME_2":"Polomolok","ID_3":37210,"NAME_3":"Pagalungan","NL_NAME_3":"","VARNAME_3":"","TYPE_3":"Barangay","ENGTYPE_3":"Village","PROVINCE":"South Cotabato","REGION":"SOCCSKSARGEN (Region XII)"},"geometry":{"type":"MultiPolygon","coordinates":[[[[125.04879,6.23726],[125.039383,6.22854],[125.031418,6.21995],[125.026047,6.21603],[125.024818,6.21709],[125.015289,6.22705],[125.018181,6.23184],[125.022232,6.22999],[125.040291,6.24566],[125.04879,6.23726]]]]}}