{"type":"Feature","properties":{"ID_0":177,"ISO":"PHL","NAME_0":"Philippines","ID_1":80,"NAME_1":"Zamboanga del Norte","ID_2":1592,"NAME_2":"Pres. Manuel A. Roxas","ID_3":40480,"NAME_3":"Tanayan","NL_NAME_3":"","VARNAME_3":"","TYPE_3":"Barangay","ENGTYPE_3":"Village","PROVINCE":"Zamboanga del Norte","REGION":"Zamboanga Peninsula (Region IX)"},"geometry":{"type":"MultiPolygon","coordinates":[[[[123.210548,8.49265],[123.21489,8.49339],[123.219391,8.49398],[123.21846,8.48448],[123.220947,8.47812],[123.220711,8.47514],[123.219467,8.47161],[123.217407,8.4702],[123.209663,8.46796],[123.202316,8.47115],[123.19973,8.47296],[123.207367,8.48187],[123.209557,8.48901],[123.210548,8.49265]]]]}}