{"type":"Feature","properties":{"ID_0":177,"ISO":"PHL","NAME_0":"Philippines","ID_1":42,"NAME_1":"Lanao del Sur","ID_2":848,"NAME_2":"Saguiaran","ID_3":21244,"NAME_3":"Pagalamatan","NL_NAME_3":"","VARNAME_3":"","TYPE_3":"Barangay","ENGTYPE_3":"Village","PROVINCE":"Lanao del Sur","REGION":"Autonomous Region of Muslim Mindanao (ARMM)"},"geometry":{"type":"MultiPolygon","coordinates":[[[[124.263252,8.0364],[124.263924,8.03543],[124.262932,8.03418],[124.259773,8.03047],[124.258163,8.03286],[124.262894,8.03699],[124.263252,8.0364]]]]}}