{"type":"Feature","properties":{"ID_0":177,"ISO":"PHL","NAME_0":"Philippines","ID_1":3,"NAME_1":"Agusan del Sur","ID_2":49,"NAME_2":"San Luis","ID_3":765,"NAME_3":"Don Pedro","NL_NAME_3":"","VARNAME_3":"","TYPE_3":"Barangay","ENGTYPE_3":"Village","PROVINCE":"Agusan del Sur","REGION":"Caraga (Region XIII)"},"geometry":{"type":"MultiPolygon","coordinates":[[[[125.721802,8.55095],[125.729912,8.54007],[125.728577,8.53949],[125.725906,8.53962],[125.723999,8.53979],[125.722137,8.53966],[125.715927,8.53776],[125.708069,8.55126],[125.721802,8.55095]]]]}}