{"type":"Feature","properties":{"ID_0":177,"ISO":"PHL","NAME_0":"Philippines","ID_1":23,"NAME_1":"Catanduanes","ID_2":414,"NAME_2":"San Miguel","ID_3":9837,"NAME_3":"Poblacion District III","NL_NAME_3":"","VARNAME_3":"","TYPE_3":"Barangay","ENGTYPE_3":"Village","PROVINCE":"Catanduanes","REGION":"Bicol Region (Region V)"},"geometry":{"type":"MultiPolygon","coordinates":[[[[124.307213,13.64228],[124.306198,13.64021],[124.305656,13.63842],[124.257027,13.63786],[124.254608,13.64211],[124.302673,13.64221],[124.307213,13.64228]]]]}}