{"type":"Feature","properties":{"ID_0":177,"ISO":"PHL","NAME_0":"Philippines","ID_1":79,"NAME_1":"Zambales","ID_2":1572,"NAME_2":"San Marcelino","ID_3":40010,"NAME_3":"Lucero","NL_NAME_3":"","VARNAME_3":"Poblacion","TYPE_3":"Barangay","ENGTYPE_3":"Village","PROVINCE":"Zambales","REGION":"Central Luzon (Region III)"},"geometry":{"type":"MultiPolygon","coordinates":[[[[120.158722,15.0046],[120.163773,15.00305],[120.16803,15.00094],[120.172462,14.99975],[120.170776,14.98947],[120.164337,14.99002],[120.15921,14.99008],[120.158836,14.99406],[120.158722,15.0046]]]]}}