{"type":"Feature","properties":{"ID_0":177,"ISO":"PHL","NAME_0":"Philippines","ID_1":36,"NAME_1":"Iloilo","ID_2":686,"NAME_2":"Santa Barbara","ID_3":17113,"NAME_3":"Cadagmayan Sur","NL_NAME_3":"","VARNAME_3":"","TYPE_3":"Barangay","ENGTYPE_3":"Village","PROVINCE":"Iloilo","REGION":"Western Visayas (Region VI)"},"geometry":{"type":"MultiPolygon","coordinates":[[[[122.503754,10.82331],[122.51696,10.82105],[122.510323,10.81475],[122.509064,10.81582],[122.506233,10.81457],[122.502121,10.81412],[122.4972,10.81265],[122.497704,10.81744],[122.501213,10.82119],[122.503754,10.82331]]]]}}