{"type":"Feature","properties":{"ID_0":177,"ISO":"PHL","NAME_0":"Philippines","ID_1":60,"NAME_1":"Pampanga","ID_2":1235,"NAME_2":"Santa Rita","ID_3":31952,"NAME_3":"San Jose","NL_NAME_3":"","VARNAME_3":"Poblacion","TYPE_3":"Barangay","ENGTYPE_3":"Village","PROVINCE":"Pampanga","REGION":"Central Luzon (Region III)"},"geometry":{"type":"MultiPolygon","coordinates":[[[[120.632362,14.99231],[120.634941,14.99554],[120.635803,14.99464],[120.636124,14.99424],[120.63784,14.99206],[120.637367,14.99068],[120.636459,14.98988],[120.635262,14.98808],[120.632362,14.99231]]]]}}