{"type":"Feature","properties":{"ID_0":177,"ISO":"PHL","NAME_0":"Philippines","ID_1":25,"NAME_1":"Cebu","ID_2":486,"NAME_2":"Sibonga","ID_3":11777,"NAME_3":"Can-Aga","NL_NAME_3":"","VARNAME_3":"","TYPE_3":"Barangay","ENGTYPE_3":"Village","PROVINCE":"Cebu","REGION":"Central Visayas (Region VII)"},"geometry":{"type":"MultiPolygon","coordinates":[[[[123.557701,10.00748],[123.558907,9.99827],[123.558327,9.98006],[123.556213,9.98042],[123.539253,9.98427],[123.54393,10.00896],[123.557701,10.00748]]]]}}