{"type":"Feature","properties":{"ID_0":177,"ISO":"PHL","NAME_0":"Philippines","ID_1":58,"NAME_1":"Oriental Mindoro","ID_2":1191,"NAME_2":"Socorro","ID_3":30970,"NAME_3":"Zone I","NL_NAME_3":"","VARNAME_3":"Poblacion","TYPE_3":"Barangay","ENGTYPE_3":"Village","PROVINCE":"Oriental Mindoro","REGION":"MIMAROPA (Region IV-B)"},"geometry":{"type":"MultiPolygon","coordinates":[[[[121.4133,13.07058],[121.409477,13.06167],[121.407333,13.06376],[121.40538,13.06647],[121.401947,13.06783],[121.403587,13.07126],[121.403763,13.07366],[121.404182,13.07617],[121.408043,13.07484],[121.410912,13.07277],[121.4133,13.07058]]]]}}