{"type":"Feature","properties":{"ID_0":177,"ISO":"PHL","NAME_0":"Philippines","ID_1":41,"NAME_1":"Lanao del Norte","ID_2":811,"NAME_2":"Tagoloan","ID_3":20231,"NAME_3":"Dalamas","NL_NAME_3":"","VARNAME_3":"","TYPE_3":"Barangay","ENGTYPE_3":"Village","PROVINCE":"Lanao del Norte","REGION":"Northern Mindanao (Region X)"},"geometry":{"type":"MultiPolygon","coordinates":[[[[124.290466,8.17072],[124.294647,8.17226],[124.291519,8.16822],[124.264977,8.15132],[124.256027,8.15303],[124.268143,8.16058],[124.290466,8.17072]]]]}}