{"type":"Feature","properties":{"ID_0":177,"ISO":"PHL","NAME_0":"Philippines","ID_1":55,"NAME_1":"Nueva Ecija","ID_2":1149,"NAME_2":"Talugtug","ID_3":30106,"NAME_3":"Pangit","NL_NAME_3":"","VARNAME_3":"","TYPE_3":"Barangay","ENGTYPE_3":"Village","PROVINCE":"Nueva Ecija","REGION":"Central Luzon (Region III)"},"geometry":{"type":"MultiPolygon","coordinates":[[[[120.8302,15.76361],[120.83197,15.76355],[120.841263,15.76257],[120.835564,15.75272],[120.838707,15.74196],[120.836197,15.73899],[120.821388,15.7481],[120.8302,15.76361]]]]}}