{"type":"Feature","properties":{"ID_0":177,"ISO":"PHL","NAME_0":"Philippines","ID_1":82,"NAME_1":"Zamboanga Sibugay","ID_2":1645,"NAME_2":"Talusan","ID_3":41877,"NAME_3":"Sagay","NL_NAME_3":"","VARNAME_3":"","TYPE_3":"Barangay","ENGTYPE_3":"Village","PROVINCE":"Zamboanga Sibugay","REGION":"Zamboanga Peninsula (Region IX)"},"geometry":{"type":"MultiPolygon","coordinates":[[[[122.843246,7.39839],[122.849251,7.39108],[122.853531,7.3791],[122.857323,7.36558],[122.846764,7.35576],[122.846077,7.35777],[122.839897,7.36869],[122.833366,7.37906],[122.827278,7.38836],[122.843246,7.39839]]]]}}