{"type":"Feature","properties":{"ID_0":177,"ISO":"PHL","NAME_0":"Philippines","ID_1":80,"NAME_1":"Zamboanga del Norte","ID_2":1602,"NAME_2":"Tampilisan","ID_3":40747,"NAME_3":"Balacbaan","NL_NAME_3":"","VARNAME_3":"","TYPE_3":"Barangay","ENGTYPE_3":"Village","PROVINCE":"Zamboanga del Norte","REGION":"Zamboanga Peninsula (Region IX)"},"geometry":{"type":"MultiPolygon","coordinates":[[[[122.64798,7.95162],[122.662956,7.95229],[122.662376,7.94382],[122.661797,7.93582],[122.662933,7.92972],[122.660782,7.92894],[122.656593,7.92742],[122.646667,7.9223],[122.645653,7.93056],[122.646446,7.9473],[122.64798,7.95162]]]]}}