{"type":"Feature","properties":{"ID_0":177,"ISO":"PHL","NAME_0":"Philippines","ID_1":43,"NAME_1":"Leyte","ID_2":895,"NAME_2":"Tanauan","ID_3":22972,"NAME_3":"Bangon","NL_NAME_3":"","VARNAME_3":"","TYPE_3":"Barangay","ENGTYPE_3":"Village","PROVINCE":"Leyte","REGION":"Eastern Visayas (Region VIII)"},"geometry":{"type":"MultiPolygon","coordinates":[[[[124.984283,11.08457],[124.986794,11.07733],[124.986298,11.07384],[124.972794,11.07263],[124.973778,11.07478],[124.971619,11.07888],[124.984283,11.08457]]]]}}