{"type":"Feature","properties":{"ID_0":177,"ISO":"PHL","NAME_0":"Philippines","ID_1":23,"NAME_1":"Catanduanes","ID_2":415,"NAME_2":"Viga","ID_3":9854,"NAME_3":"Del Pilar","NL_NAME_3":"","VARNAME_3":"","TYPE_3":"Barangay","ENGTYPE_3":"Village","PROVINCE":"Catanduanes","REGION":"Bicol Region (Region V)"},"geometry":{"type":"MultiPolygon","coordinates":[[[[124.300697,13.86089],[124.30687,13.85636],[124.295097,13.85279],[124.287918,13.8517],[124.284531,13.86223],[124.288483,13.86569],[124.293777,13.8651],[124.295807,13.86418],[124.297287,13.86325],[124.298424,13.86233],[124.300697,13.86089]]]]}}