{"type":"Feature","properties":{"ID_0":177,"ISO":"PHL","NAME_0":"Philippines","ID_1":43,"NAME_1":"Leyte","ID_2":898,"NAME_2":"Villaba","ID_3":23049,"NAME_3":"Cabungahan","NL_NAME_3":"","VARNAME_3":"","TYPE_3":"Barangay","ENGTYPE_3":"Village","PROVINCE":"Leyte","REGION":"Eastern Visayas (Region VIII)"},"geometry":{"type":"MultiPolygon","coordinates":[[[[124.446327,11.24984],[124.446114,11.24853],[124.444366,11.24632],[124.44223,11.24424],[124.440338,11.24448],[124.438263,11.24506],[124.435722,11.24604],[124.438293,11.25294],[124.446327,11.24984]]]]}}