{"type":"Feature","properties":{"ID_0":177,"ISO":"PHL","NAME_0":"Philippines","ID_1":19,"NAME_1":"Camarines Norte","ID_2":344,"NAME_2":"Vinzons","ID_3":8011,"NAME_3":"Barangay  I","NL_NAME_3":"","VARNAME_3":"Poblacion","TYPE_3":"Barangay","ENGTYPE_3":"Village","PROVINCE":"Camarines Norte","REGION":"Bicol Region (Region V)"},"geometry":{"type":"MultiPolygon","coordinates":[[[[122.905357,14.18953],[122.906647,14.18706],[122.908524,14.18442],[122.909973,14.18193],[122.91053,14.18089],[122.912178,14.17775],[122.910027,14.17621],[122.907806,14.18055],[122.904907,14.18635],[122.905197,14.18711],[122.905342,14.18857],[122.905357,14.18953]]]]}}